astr/__init__.py
astr/_modidx.py
astr/_tmp.py
astr/core.py
astr-0.0.11.dist-info/LICENSE
astr-0.0.11.dist-info/METADATA
astr-0.0.11.dist-info/WHEEL
astr-0.0.11.dist-info/entry_points.txt
astr-0.0.11.dist-info/top_level.txt
astr-0.0.11.dist-info/RECORD
