Metadata-Version: 2.1
Name: astr
Version: 0.0.11
Summary: astr (attribute string) for defined getter / setter methods
Home-page: https://github.com/dsm-72/astr
Author: dsm-72
Author-email: sumner.magruder@yale.edu
License: Apache Software License 2.0
Keywords: attr str attribute string astr attrstr python alias type astr typ get set instance ins insattr getter setter
Classifier: Development Status :: 4 - Beta
Classifier: Intended Audience :: Developers
Classifier: Natural Language :: English
Classifier: Programming Language :: Python :: 3.11
Classifier: License :: OSI Approved :: Apache Software License
Requires-Python: >=3.11
License-File: LICENSE
Provides-Extra: dev
